{
	"format_version": "1.10.0",
	"minecraft:attachable": {
		"description": {
			"identifier": "hair:minato_verde_c",
			"item": {
				"hair:minato_verde_c": "query.owner_identifier == 'minecraft:player'"
			},
			"materials": {
				"default": "armor",
				"enchanted": "armor_enchanted"
			},
			"textures": {
				"default": "textures/hair/hair_kakashi_verde_c",
				"enchanted": "textures/misc/enchanted_item_glint"
			},
			"geometry": {
				"default": "geometry.hair_minato"
			},
			"scripts": {
				"parent_setup": "variable.chest_layer_visible = 0.0;"
			},
			"render_controllers": [
				"controller.render.armor"
			]
		}
	}
}
