{
	"format_version": "1.12.0",
	"minecraft:geometry": [
		{
			"description": {
				"identifier": "geometry.guizo",
				"texture_width": 32,
				"texture_height": 32,
				"visible_bounds_width": 2,
				"visible_bounds_height": 1.5,
				"visible_bounds_offset": [0, 0.25, 0]
			},
			"bones": [
				{
					"name": "guizo",
					"pivot": [-4, 0, -1]
				},
				{
					"name": "2",
					"parent": "guizo",
					"pivot": [-3.41451, 0.16, -0.5843],
					"rotation": [0, -20, 0],
					"cubes": [
						{
							"origin": [-3.32, 0, -6.0757],
							"size": [0.32, 0.32, 5.32],
							"pivot": [-3.41451, 0.16, -1.4157],
							"rotation": [-6.67406, -55.1259, -3.76893],
							"uv": {
								"north": {"uv": [24, 0], "uv_size": [-8, 8]},
								"east": {"uv": [24, 0], "uv_size": [-8, 8]},
								"south": {"uv": [24, 0], "uv_size": [-8, 8]},
								"west": {"uv": [24, 0], "uv_size": [-8, 8]},
								"up": {"uv": [16, 0], "uv_size": [8, 8]},
								"down": {"uv": [16, 0], "uv_size": [8, 8]}
							}
						},
						{
							"origin": [-5.6, 0, -7.8],
							"size": [1.6, 1.6, 1.6],
							"pivot": [-4, 0, -1],
							"rotation": [0, -67.5, 0],
							"uv": {
								"north": {"uv": [16, 8], "uv_size": [-8, 8]},
								"east": {"uv": [8, 0], "uv_size": [-8, 8]},
								"south": {"uv": [8, 0], "uv_size": [-8, 8]},
								"west": {"uv": [8, 0], "uv_size": [-8, 8]},
								"up": {"uv": [8, 0], "uv_size": [8, 8]},
								"down": {"uv": [0, 0], "uv_size": [8, 8]}
							}
						}
					]
				},
				{
					"name": "1",
					"parent": "guizo",
					"pivot": [-3.41451, 0.16, -0.5843],
					"cubes": [
						{
							"origin": [-3.32, 0, -1.2443],
							"size": [0.32, 0.32, 5.32],
							"pivot": [-3.41451, 0.16, -0.5843],
							"rotation": [6.67406, 55.1259, -3.76893],
							"uv": {
								"north": {"uv": [16, 0], "uv_size": [8, 8]},
								"east": {"uv": [16, 0], "uv_size": [8, 8]},
								"south": {"uv": [16, 0], "uv_size": [8, 8]},
								"west": {"uv": [16, 0], "uv_size": [8, 8]},
								"up": {"uv": [16, 8], "uv_size": [8, -8]},
								"down": {"uv": [16, 8], "uv_size": [8, -8]}
							}
						},
						{
							"origin": [0.43713, 0, 1.2352],
							"size": [1.6, 1.6, 1.6],
							"pivot": [1.23713, 0.8, 2.0352],
							"rotation": [0, 77.5, 0],
							"uv": {
								"north": {"uv": [0, 0], "uv_size": [8, 8]},
								"east": {"uv": [0, 0], "uv_size": [8, 8]},
								"south": {"uv": [8, 8], "uv_size": [8, 8]},
								"west": {"uv": [0, 0], "uv_size": [8, 8]},
								"up": {"uv": [8, 8], "uv_size": [8, -8]},
								"down": {"uv": [0, 8], "uv_size": [8, -8]}
							}
						}
					]
				}
			]
		}
	]
}